{"card_name": "UGU04 Crestbreak Hydra", "color": "UG", "rarity": "uncommon", "type": "Creature \u2013 Hydra", "number": 232, "color_identity": "UG", "cost": "{X}{GU}", "rules_text": "Defender, vigilance, reach\nUGU04 Crestbreak Hydra enters with X +1/+1 counters on it.\n[i]Finale \u2013[/i] Whenever an enchantment is put into your graveyard from the battlefield, UGU04 Crestbreak Hydra loses defender until end of turn.", "flavor_text": "[i][/i]", "pt": "0/0", "special_text": "", "shape": "normal", "set": "VGE", "loyalty": "", "artist": "Tomasz Ryger", "notes": "", "image_type": "png"}