{"card_name": "CC03 Requiem Automata", "color": "", "rarity": "common", "type": "Artifact Creature", "number": 250, "color_identity": "C", "cost": "{5}", "rules_text": "[i]Finale \u2013 [/i]Whenever an enchantment is put into your graveyard from the battlefield, Requiem Automata gets +2/+2 until end of turn.", "flavor_text": "[i]They were built to sing the last song anyone will ever hear.[/i]", "pt": "3/3", "special_text": "", "shape": "normal", "set": "VGE", "loyalty": "", "artist": "Thomas Chamberlain-Keen", "notes": "", "image_type": "png"}