{"card_name": "MR02 Dreadwyrm Nizoont", "color": "R", "rarity": "mythic", "type": "Creature \u2013 Elder Dragon", "number": 139, "color_identity": "R", "cost": "{3}{R}{R}{R}", "rules_text": "Flying\nWhen Dreadwyrm Nizoont enters the battlefield, exile the top three cards of your library, for each card target player may pay 2 life, if they do put that card into your graveyard, then you may cast a card exiled this way without paying its mana cost.\n{R}{R}{R}: Return Dreadwyrm Nizoont from your graveyard to the battlefield transformed.", "flavor_text": "[i][/i]", "pt": "6/6", "special_text": "", "shape": "transform double faced", "set": "XC3", "loyalty": "", "artist": "Monolith Soft", "card_name2": "Nizoont's Grave", "color2": "R", "type2": "Legendary Artifact", "cost2": "", "rules_text2": "Whenever you cast a spell from exile you may pay {R}, if you do Nizoont's Grave deals 2 damage to each opponent.\n{4}, {T}: Transform Nizoont's Grave. It gains \u201cWhen this card would be put into a graveyard from anywhere exile it instead.\u201d", "flavor_text2": "[i][/i]", "pt2": "", "special_text2": "", "loyalty2": "", "artist2": "Monolith Soft", "notes": "Superboss", "image_type": "png"}