{"card_name": "CG15 Explore", "color": "G", "rarity": "common", "type": "Sorcery", "number": 173, "color_identity": "G", "cost": "{1}{G}", "rules_text": "You may play an additional land this turn.\nDraw a card.", "flavor_text": "[i]\u201cThink about it. Even if humans were gone, it would shine on, illuminating the land beneath.\u201d \u2014 Noah[/i]", "pt": "", "special_text": "", "shape": "normal", "set": "XC3", "loyalty": "", "artist": "Monolith Soft", "notes": "#Reprint", "image_type": "png"}