{"card_name": "UM01 Smith's Hammer", "color": "WU", "rarity": "uncommon", "type": "Artifact \u2013 Equipment", "number": 221, "color_identity": "WU", "cost": "{W}{U}", "rules_text": "Equipped creature has \u201cWhenever this creature deals combat damage to a player, untap it and draw a card.\u201d and \u201c{W}{U}, {T}: Transform target Nopon, or noncreature permanent you control.\u201d\nEquip {1}", "flavor_text": "[i][/i]", "pt": "", "special_text": "", "shape": "transform double faced", "set": "XC3", "loyalty": "", "artist": "Monolith Soft", "card_name2": "Nopon Smith", "color2": "WU", "type2": "Creature \u2013 Nopon Artificer", "cost2": "", "rules_text2": "Vigilance\nWhenever Nopon Smith deals combat damage to a player or battle, add {W}{U}.\n{W}{U}: Transform another target Nopon, or noncreature permanent you control.", "flavor_text2": "[i]\u201cIf anything happen to Ship, Samon die of heart fracture.\u201d \u2014 Samon, Nopon Smith[/i]", "pt2": "5/4", "special_text2": "", "loyalty2": "", "artist2": "Monolith Soft", "notes": "", "image_type": "png"}