{"card_name": "RX01 Colony Gamma", "color": "", "rarity": "rare", "type": "Legendary Artifact Land \u2013 Vehicle", "number": 240, "color_identity": "W", "cost": "", "rules_text": "RX01 Colony Gamma enters the battlefield tapped unless you tap an untapped creature you control.\nVigilance\n{T}: Add {W}.\nCrew 4 [i](Tap any number of creatures you control with total power 4 or more: This Vehicle becomes an artifact creature until end of turn.)[/i]", "flavor_text": "[i][/i]", "pt": "3/6", "special_text": "", "shape": "normal", "set": "XC3", "loyalty": "", "artist": "Monolith Soft", "notes": "", "image_type": "png"}