{"card_name": "RX05 Colony Tau", "color": "", "rarity": "rare", "type": "Legendary Artifact Land \u2013 Vehicle", "number": 244, "color_identity": "G", "cost": "", "rules_text": "RX05 Colony Tau enters the battlefield tapped unless you tap an untapped creature you control.\nTrample\n{T}: Add {G}.\nCrew 4 [i](Tap any number of creatures you control with total power 4 or more: This Vehicle becomes an artifact creature until end of turn.)[/i]", "flavor_text": "[i][/i]", "pt": "5/5", "special_text": "", "shape": "normal", "set": "XC3", "loyalty": "", "artist": "Monolith Soft", "notes": "enters the battlefield tapped balance note\nAND/OR\nremove land type", "image_type": "png"}